deepdrive_capture.cp35-win_amd64.pyd
deepdrive_client.cp35-win_amd64.pyd
deepdrive-2.0.20190722213951.dist-info/LICENSE.md
deepdrive-2.0.20190722213951.dist-info/METADATA
deepdrive-2.0.20190722213951.dist-info/WHEEL
deepdrive-2.0.20190722213951.dist-info/top_level.txt
deepdrive-2.0.20190722213951.dist-info/RECORD
