Metadata-Version: 2.1
Name: deepdrive
Version: 2.0.20190722213951
Summary: Python interface to vehicle simulation running in Unreal
Home-page: https://github.com/deepdrive/deepdrive-sim
Author: deepdrive.io
Author-email: developers@deepdrive.io
License: MIT
Platform: UNKNOWN
Requires-Dist: numpy
